{"name":"C\u00f3digo X","short_name":"C\u00f3digo X","description":"Solu\u00e7\u00f5es para Reparadores","icons":[{"src":"https:\/\/aplicativo.appcodigox.com\/wp-content\/uploads\/2021\/06\/icone192.png","sizes":"192x192","type":"image\/png","purpose":"any"},{"src":"https:\/\/aplicativo.appcodigox.com\/wp-content\/uploads\/2021\/06\/icone192.png","sizes":"192x192","type":"image\/png","purpose":"maskable"},{"src":"https:\/\/aplicativo.appcodigox.com\/wp-content\/uploads\/2021\/10\/logo-splash-certo-app.png","sizes":"512x512","type":"image\/png","purpose":"any"},{"src":"https:\/\/aplicativo.appcodigox.com\/wp-content\/uploads\/2021\/10\/logo-splash-certo-app.png","sizes":"512x512","type":"image\/png","purpose":"maskable"},{"src":"https:\/\/aplicativo.appcodigox.com\/wp-content\/uploads\/2023\/12\/icone.png","sizes":"512x512","type":"image\/png","purpose":"monochrome"}],"background_color":"#ffffff","theme_color":"#8c0404","display":"standalone","dir":"ltr","orientation":"portrait","start_url":".","categories":["education"],"scope":"\/","shortcuts":[{"name":"C\u00f3digo X","url":"\/","description":"Solu\u00e7\u00f5es para Reparadores","icons":[{"src":"https:\/\/aplicativo.appcodigox.com\/wp-content\/uploads\/2021\/06\/icone192.png","sizes":"192x192"}]}],"related_applications":[{"id":"com.appcodigox.aplicativo.twa","platform":"play","url":"https:\/\/play.google.com\/store\/apps\/details?id=com.appcodigox.aplicativo.twa"}]}